src/__init__.py
src/util.py
src/vibase.py
vibase-0.1.0.dist-info/LICENSE
vibase-0.1.0.dist-info/METADATA
vibase-0.1.0.dist-info/WHEEL
vibase-0.1.0.dist-info/entry_points.txt
vibase-0.1.0.dist-info/top_level.txt
vibase-0.1.0.dist-info/RECORD
