Metadata-Version: 2.1
Name: vibase
Version: 0.1.0
Summary: Edit a database table using the VIM editor
Home-page: https://github.com/BnMcGn/vibase
Author: Ben McGunigle
Author-email: bnmcgn@gmail.com
License: UNKNOWN
Download-URL: https://github.com/BnMcGn/vibase/archive/0.1.0.tar.gzip
Platform: UNKNOWN
License-File: LICENSE
